eburger/__init__.py
eburger/main.py
eburger/serializer.py
eburger/settings.py
eburger/template_utils.py
eburger/templates/emit_after_external_call.yaml
eburger/templates/missing_reentrancy_guard.yaml
eburger/templates/missing_zero_address_check.yaml
eburger/templates/modifier_without_proper_enforcement.yaml
eburger/templates/tx_origin_used_for_access_control.yaml
eburger/templates/unbounded_loop.yaml
eburger/templates/unchecked_call_return.yaml
eburger/templates/unchecked_chainlink_oracle_price.yaml
eburger/templates/unspecific_pragma_detector.yaml
eburger/templates/unverified_from_address_in_transfer.yaml
eburger/templates/use_of_approve_with_max_allowance.yaml
eburger/templates/use_of_encodepacked.yaml
eburger/templates/use_of_safetransferlib.yaml
eburger/templates/use_of_transfer_or_send_on_payable.yaml
eburger/templates/use_of_unsafe_mint.yaml
eburger/utils/cli_args.py
eburger/utils/compilers.py
eburger/utils/filesystem.py
eburger/utils/helpers.py
eburger/utils/installers.py
eburger/utils/logger.py
eburger/utils/outputs.py
eburger/yaml_parser.py
eburger-1.0.7.dist-info/LICENSE
eburger-1.0.7.dist-info/METADATA
eburger-1.0.7.dist-info/WHEEL
eburger-1.0.7.dist-info/entry_points.txt
eburger-1.0.7.dist-info/RECORD
