Metadata-Version: 2.1
Name: eburger
Version: 1.0.7
Summary: 
Author: tomie
Author-email: admin@forefy.com
Requires-Python: >=3.10,<4.0
Classifier: Programming Language :: Python :: 3
Classifier: Programming Language :: Python :: 3.10
Classifier: Programming Language :: Python :: 3.11
Classifier: Programming Language :: Python :: 3.12
Requires-Dist: argparse (>=1.4.0,<2.0.0)
Requires-Dist: packaging (>=23.2,<24.0)
Requires-Dist: prettytable (>=3.9.0,<4.0.0)
Requires-Dist: pygount (>=1.6.1,<2.0.0)
Requires-Dist: pyyaml (>=6.0.1,<7.0.0)
